autolms-0.4.3.dist-info/METADATA
autolms-0.4.3.dist-info/WHEEL
autolms-0.4.3.dist-info/entry_points.txt
autolms-0.4.3.dist-info/licenses/LICENSE
autolms/__init__.py
autolms/config.py
autolms/core.py
autolms/main.py
autolms-0.4.3.dist-info/RECORD
