Metadata-Version: 2.1
Name: AutoLMS
Version: 0.4.3
Summary: Automation of getting into LMS classes
Author-Email: AmirMohammad Hosseini Nasab <awmirhn@gmail.com>
License: MIT
Requires-Python: >=3.12
Requires-Dist: selenium>=4.21.0
Requires-Dist: fire>=0.6.0
Requires-Dist: pyyaml>=6.0.1
Requires-Dist: InquirerPy>=0.3.4
Requires-Dist: schedule>=1.2.2
